xarray_tensorstore.py
xarray_tensorstore-0.2.0.dist-info/licenses/LICENSE
xarray_tensorstore-0.2.0.dist-info/METADATA
xarray_tensorstore-0.2.0.dist-info/WHEEL
xarray_tensorstore-0.2.0.dist-info/top_level.txt
xarray_tensorstore-0.2.0.dist-info/RECORD
