Metadata-Version: 2.4
Name: xarray-tensorstore
Version: 0.2.0
Author: Google LLC
Author-email: noreply@google.com
License: Apache-2.0
Requires-Python: >=3.10
License-File: LICENSE
Requires-Dist: numpy
Requires-Dist: xarray
Requires-Dist: zarr
Requires-Dist: tensorstore
Provides-Extra: tests
Requires-Dist: absl-py; extra == "tests"
Requires-Dist: pandas; extra == "tests"
Requires-Dist: pytest; extra == "tests"
Requires-Dist: dask; extra == "tests"
Dynamic: author
Dynamic: author-email
Dynamic: license
Dynamic: license-file
Dynamic: provides-extra
Dynamic: requires-dist
Dynamic: requires-python
